pyutttils/Member.py
pyutttils/Semester.py
pyutttils/__init__.py
pyutttils/utils.py
pyutttils/utt_auth.py
tests/TestMember.py
tests/TestSemester.py
tests/__init__.py
pyutttils-0.1.0.dist-info/LICENCE.txt
pyutttils-0.1.0.dist-info/METADATA
pyutttils-0.1.0.dist-info/WHEEL
pyutttils-0.1.0.dist-info/top_level.txt
pyutttils-0.1.0.dist-info/RECORD
