Metadata-Version: 2.1
Name: pyutttils
Version: 0.1.0
Summary: Package de fonctions utilitaires pour l'Université de Technologie de Troyes (UTT)
Home-page: https://github.com/larueli/pyutttils
Author: Ivann LARUELLE
Author-email: ivann@laruelle.me
License: MIT
Platform: UNKNOWN
Classifier: Programming Language :: Python :: 3
Classifier: License :: OSI Approved :: MIT License
Classifier: Operating System :: OS Independent
Requires-Python: >=3.6
License-File: LICENCE.txt
Requires-Dist: requests
